django_database_postgresql_aad_backend/__init__.py
django_database_postgresql_aad_backend/base.py
django_database_postgresql_aad_backend/mixins.py
django_database_postgresql_aad_backend-0.0.1.dist-info/LICENSE.txt
django_database_postgresql_aad_backend-0.0.1.dist-info/METADATA
django_database_postgresql_aad_backend-0.0.1.dist-info/WHEEL
django_database_postgresql_aad_backend-0.0.1.dist-info/top_level.txt
django_database_postgresql_aad_backend-0.0.1.dist-info/RECORD
