Metadata-Version: 2.1
Name: django-database-postgresql-aad-backend
Version: 0.0.1
Summary: Django database backend for Azure Postgresql that adds AAD authentication
Home-page: https://github.com/younux/django-database-postgresql-aad-backend
Author: Younes
Author-email: b.younes.h@gmail.com
License: MIT
Download-URL: https://github.com/younux/django-database-postgresql-aad-backend/releases/download/v0.0.1/django_database_postgresql_aad_backend-v0.0.1.tar.gz
Keywords: Django,Database,Backend,Postgresql,Azure,AAD
Platform: UNKNOWN
Classifier: Development Status :: 3 - Alpha
Classifier: Intended Audience :: Developers
Classifier: Topic :: Software Development :: Build Tools
Classifier: License :: OSI Approved :: MIT License
Classifier: Programming Language :: Python :: 3
Classifier: Programming Language :: Python :: 3.8
Requires-Dist: asgiref (==3.3.1)
Requires-Dist: azure-core (==1.10.0)
Requires-Dist: azure-identity (==1.5.0)
Requires-Dist: certifi (==2020.12.5)
Requires-Dist: cffi (==1.14.4)
Requires-Dist: chardet (==4.0.0)
Requires-Dist: cryptography (==3.3.1)
Requires-Dist: Django (==3.1.5)
Requires-Dist: idna (==2.10)
Requires-Dist: msal (==1.8.0)
Requires-Dist: msal-extensions (==0.3.0)
Requires-Dist: portalocker (==1.7.1)
Requires-Dist: psycopg2-binary (==2.8.6)
Requires-Dist: pycparser (==2.20)
Requires-Dist: PyJWT (==1.7.1)
Requires-Dist: pytz (==2020.5)
Requires-Dist: requests (==2.25.1)
Requires-Dist: six (==1.15.0)
Requires-Dist: sqlparse (==0.4.1)
Requires-Dist: urllib3 (==1.26.2)
